{"is_source_file": true, "format": "JavaScript/JSX", "description": "This file defines a React component for a Settings page in a frontend application. It imports layout and UI components, and renders a settings interface with theme options and API configuration details.", "external_files": ["src/layouts/AppLayout", "src/components/UI"], "external_methods": [], "published": [], "classes": [], "methods": [{"name": "Settings()", "description": "React functional component rendering the Settings page, providing options for theme customization and API integration configuration.", "scope": "", "scopeKind": ""}], "calls": ["React", "AppLayout", "Card", "process.env.REACT_APP_API_BASE"], "search-terms": ["Settings.jsx", "React component", "API Integration", "Theme selection", "Environment variable", "Settings page"], "state": 2, "file_id": 26, "knowledge_revision": 115, "git_revision": "272b4b3e24e93c4d2315a7253e97948c595e7f39", "revision_history": [{"52": ""}, {"115": "272b4b3e24e93c4d2315a7253e97948c595e7f39"}], "ctags": [{"_type": "tag", "name": "Settings", "path": "/home/kavia/workspace/code-generation/sales-growth-tracker-26634-26727/crm_frontend/src/pages/Settings.jsx", "pattern": "/^export default function Settings() {$/", "language": "JavaScript", "kind": "function", "signature": "()"}], "hash": "2abfc022e7a3ab780393eb7db49b22c9", "format-version": 4, "code-base-name": "crm_frontend", "filename": "crm_frontend/src/pages/Settings.jsx"}